pylaxz/__init__.py
pylaxz/__main__.py
pylaxz/__version__.py
pylaxz/data/settings.ini
pylaxz/iots/__init__.py
pylaxz/iots/jnano.py
pylaxz/iots/rpi.py
pylaxz/matrics/__init__.py
pylaxz/matrics/_length.py
pylaxz/orm/__init__.py
pylaxz/settings/__init__.py
pylaxz/settings/commands.db
pylaxz/settings/dbcore.py
pylaxz/shells/checkx.sh
pylaxz/shells/dkx.sh
pylaxz/shells/dox.sh
pylaxz/shells/getdata.py
pylaxz/shells/howx.sh
pylaxz/shells/outlinex.sh
pylaxz/shells/pyParser.py
pylaxz/shells/scriptx.sh
pylaxz/shells/sish.sh
pylaxz/shells/sqlx.sh
pylaxz/shells/sysx.sh
pylaxz/shells/xx.sh
pylaxz/utils/__init__.py
pylaxz/utils/_network.py
pylaxz/utils/_outlinevpn.py
pylaxz/utils/_system.py
pylaxz/utils/logxs.py
py_laxz-0.6.8.dist-info/LICENSE
py_laxz-0.6.8.dist-info/METADATA
py_laxz-0.6.8.dist-info/WHEEL
py_laxz-0.6.8.dist-info/entry_points.txt
py_laxz-0.6.8.dist-info/top_level.txt
py_laxz-0.6.8.dist-info/RECORD
