Metadata-Version: 2.1
Name: py-laxz
Version: 0.6.8
Summary: A small until for my needs.
Home-page: https://github.com/minlaxz/py-laxz
Author: Min Latt
Author-email: minminlaxz@gmail.com
License: MIT
Project-URL: Bug Reports, https://github.com/minlaxz/pylaxz/issues
Project-URL: Say Thanks!, http://saythanks.io/to/minminlaxz%40gmail.com
Project-URL: Source, https://github.com/minlaxz/py-laxz
Keywords: sample,setuptools,development,pylaxz
Platform: UNKNOWN
Classifier: Programming Language :: Python :: 3
Classifier: Programming Language :: Python :: 3 :: Only
Classifier: License :: OSI Approved :: MIT License
Classifier: Operating System :: OS Independent
Requires-Python: >=3.5, <4
Requires-Dist: rich
Requires-Dist: speedtest-cli
Requires-Dist: click
